<?xml version="1.0" encoding="UTF-8"?>
<saved>
    <saved-design>
        <id>01fcc4d8-f5f7-4428-b90b-042ac80999a3</id>
        <ts>2019-04-06T15:08:08.783+01:00</ts>
        <title>Figure 8 knot</title>
        <designer>Kit</designer>
        <comment/>
        <design>
            <preset>
                <title>Fourier 3 Term</title>
                <scale>1</scale>
                <param>
                    <name>R1</name>
                    <val>1</val>
                </param>
                <param>
                    <name>A1</name>
                    <val>20</val>
                </param>
                <param>
                    <name>P1</name>
                    <val>0</val>
                </param>
                <param>
                    <name>R2</name>
                    <val>3</val>
                </param>
                <param>
                    <name>A2</name>
                    <val>40</val>
                </param>
                <param>
                    <name>P2</name>
                    <val>0</val>
                </param>
                <param>
                    <name>R3</name>
                    <val>0</val>
                </param>
                <param>
                    <name>A3</name>
                    <val>0</val>
                </param>
                <param>
                    <name>P3</name>
                    <val>0</val>
                </param>
            </preset>
        </design>
    </saved-design>
    <saved-design>
        <id>148bafe8-0fd1-447e-bdab-b9b114ef43f8</id>
        <ts>2019-04-06T15:09:29.645+01:00</ts>
        <title>Carrick knot</title>
        <designer>Kit</designer>
        <comment/>
        <design>
            <preset>
                <title>Fourier 3 Term</title>
                <scale>1</scale>
                <param>
                    <name>R1</name>
                    <val>1</val>
                </param>
                <param>
                    <name>A1</name>
                    <val>49</val>
                </param>
                <param>
                    <name>P1</name>
                    <val>0</val>
                </param>
                <param>
                    <name>R2</name>
                    <val>3</val>
                </param>
                <param>
                    <name>A2</name>
                    <val>-2</val>
                </param>
                <param>
                    <name>P2</name>
                    <val>0</val>
                </param>
                <param>
                    <name>R3</name>
                    <val>-3</val>
                </param>
                <param>
                    <name>A3</name>
                    <val>-85</val>
                </param>
                <param>
                    <name>P3</name>
                    <val>0</val>
                </param>
            </preset>
        </design>
    </saved-design>
    <saved-design>
        <id>008f37a2-8027-4ca1-9d48-023c4cade1b5</id>
        <ts>2019-04-06T15:10:24.014+01:00</ts>
        <title>Swirl 6</title>
        <designer>Kit </designer>
        <comment/>
        <design>
            <preset>
                <title>Fourier 3 Term Relative</title>
                <scale>1</scale>
                <param>
                    <name>R1</name>
                    <val>1</val>
                </param>
                <param>
                    <name>A1</name>
                    <val>80</val>
                </param>
                <param>
                    <name>P1</name>
                    <val>0</val>
                </param>
                <param>
                    <name>R2</name>
                    <val>-6</val>
                </param>
                <param>
                    <name>A2</name>
                    <val>50</val>
                </param>
                <param>
                    <name>P2</name>
                    <val>0</val>
                </param>
                <param>
                    <name>R3</name>
                    <val>30</val>
                </param>
                <param>
                    <name>A3</name>
                    <val>22</val>
                </param>
                <param>
                    <name>P3</name>
                    <val>90</val>
                </param>
            </preset>
        </design>
    </saved-design>
    <saved-design>
        <id>3e67b070-d7c2-4c45-a514-e86bc8592151</id>
        <ts>2019-04-06T15:10:52.309+01:00</ts>
        <title>Ferris Mystery Curve</title>
        <designer>Kit</designer>
        <comment/>
        <design>
            <preset>
                <title>Fourier 3 Term Relative</title>
                <scale>1</scale>
                <param>
                    <name>R1</name>
                    <val>1</val>
                </param>
                <param>
                    <name>A1</name>
                    <val>100</val>
                </param>
                <param>
                    <name>P1</name>
                    <val>0</val>
                </param>
                <param>
                    <name>R2</name>
                    <val>6</val>
                </param>
                <param>
                    <name>A2</name>
                    <val>50</val>
                </param>
                <param>
                    <name>P2</name>
                    <val>0</val>
                </param>
                <param>
                    <name>R3</name>
                    <val>-24</val>
                </param>
                <param>
                    <name>A3</name>
                    <val>30</val>
                </param>
                <param>
                    <name>P3</name>
                    <val>-90</val>
                </param>
            </preset>
        </design>
    </saved-design>
    <saved-design>
        <id>21ccfcf1-d80f-477f-9a0f-cbc2a45a3d67</id>
        <ts>2019-04-06T15:11:23.629+01:00</ts>
        <title>Three Trefoils</title>
        <designer>Kit</designer>
        <comment/>
        <design>
            <preset>
                <title>Fourier 3 Term Relative</title>
                <scale>3</scale>
                <param>
                    <name>R1</name>
                    <val>1</val>
                </param>
                <param>
                    <name>A1</name>
                    <val>24</val>
                </param>
                <param>
                    <name>P1</name>
                    <val>0</val>
                </param>
                <param>
                    <name>R2</name>
                    <val>-3</val>
                </param>
                <param>
                    <name>A2</name>
                    <val>28</val>
                </param>
                <param>
                    <name>P2</name>
                    <val>0</val>
                </param>
                <param>
                    <name>R3</name>
                    <val>6</val>
                </param>
                <param>
                    <name>A3</name>
                    <val>33</val>
                </param>
                <param>
                    <name>P3</name>
                    <val>175</val>
                </param>
            </preset>
        </design>
    </saved-design>
    <saved-design>
        <id>7c2b4f2e-85eb-443d-afe2-4a6640364a4e</id>
        <ts>2019-04-06T16:50:59.93+01:00</ts>
        <title>Superellipse</title>
        <designer>Kit</designer>
        <comment>by Piet Hein</comment>
        <design>
            <preset>
                <title>Lame curves</title>
                <scale>20 </scale>
                <param>
                    <name>N</name>
                    <val>42</val>
                </param>
                <param>
                    <name>M</name>
                    <val>65</val>
                </param>
                <param>
                    <name>a</name>
                    <val>4</val>
                </param>
                <param>
                    <name>b</name>
                    <val>5</val>
                </param>
            </preset>
        </design>
    </saved-design>
    <saved-design>
        <id>ab2414bb-37e1-47a4-af04-b7e25eaa8a08</id>
        <ts>2019-04-06T17:34:08.809+01:00</ts>
        <title>Lissajous 3-2</title>
        <designer>Kit</designer>
        <comment/>
        <design>
            <preset>
                <title>Lissajous Figures</title>
                <scale>20</scale>
                <param>
                    <name>Fx</name>
                    <val>3</val>
                </param>
                <param>
                    <name>Ax</name>
                    <val>10</val>
                </param>
                <param>
                    <name>Px</name>
                    <val>47</val>
                </param>
                <param>
                    <name>Fy</name>
                    <val>2</val>
                </param>
                <param>
                    <name>Ay</name>
                    <val>10</val>
                </param>
            </preset>
        </design>
    </saved-design>
    <saved-design>
        <id>f3f070d8-652c-4da5-8260-818b2bc10ebc</id>
        <ts>2019-04-07T09:10:22.913+01:00</ts>
        <title>Astroid</title>
        <designer>Kit</designer>
        <comment/>
        <design>
            <preset>
                <title>Lame curves</title>
                <scale>20</scale>
                <param>
                    <name>N</name>
                    <val>79</val>
                </param>
                <param>
                    <name>M</name>
                    <val>23</val>
                </param>
                <param>
                    <name>a</name>
                    <val>5</val>
                </param>
                <param>
                    <name>b</name>
                    <val>5</val>
                </param>
            </preset>
        </design>
    </saved-design>
    <saved-design>
        <id>a453dcba-9ef4-4fd3-bce8-857e1b1287ac</id>
        <ts>2019-04-07T13:34:42.094+01:00</ts>
        <title>Engare</title>
        <designer>Kit</designer>
        <comment/>
        <design>
            <preset>
                <title>Fourier 3 Term Relative</title>
                <scale>10</scale>
                <param>
                    <name>R1</name>
                    <val>1</val>
                </param>
                <param>
                    <name>A1</name>
                    <val>10</val>
                </param>
                <param>
                    <name>P1</name>
                    <val>0</val>
                </param>
                <param>
                    <name>R2</name>
                    <val>-10</val>
                </param>
                <param>
                    <name>A2</name>
                    <val>5</val>
                </param>
                <param>
                    <name>P2</name>
                    <val>0</val>
                </param>
                <param>
                    <name>R3</name>
                    <val>30</val>
                </param>
                <param>
                    <name>A3</name>
                    <val>1.75</val>
                </param>
                <param>
                    <name>P3</name>
                    <val>0</val>
                </param>
            </preset>
        </design>
    </saved-design>
    <saved-design>
        <id>ddb12f5c-c595-498c-b168-bcc81c98697d</id>
        <ts>2019-04-08T08:24:41.725+01:00</ts>
        <title>Briaded ring - 22 crossings</title>
        <designer>Kit</designer>
        <comment/>
        <design>
            <preset>
                <title>Fourier 3 Term</title>
                <scale>1</scale>
                <param>
                    <name>R1</name>
                    <val>3</val>
                </param>
                <param>
                    <name>A1</name>
                    <val>0</val>
                </param>
                <param>
                    <name>P1</name>
                    <val>0</val>
                </param>
                <param>
                    <name>R2</name>
                    <val>8</val>
                </param>
                <param>
                    <name>A2</name>
                    <val>-7</val>
                </param>
                <param>
                    <name>P2</name>
                    <val>0</val>
                </param>
                <param>
                    <name>R3</name>
                    <val>-3</val>
                </param>
                <param>
                    <name>A3</name>
                    <val>-85</val>
                </param>
                <param>
                    <name>P3</name>
                    <val>0</val>
                </param>
            </preset>
        </design>
    </saved-design>
    <saved-design>
        <id>83de1d7b-2d9f-480d-8bcd-8221fb6be830</id>
        <ts>2019-04-08T10:44:16.294+01:00</ts>
        <title>Lame square</title>
        <designer>Kit</designer>
        <comment/>
        <design>
            <preset>
                <title>Lame curves</title>
                <scale>20</scale>
                <param>
                    <name>N</name>
                    <val>46</val>
                </param>
                <param>
                    <name>M</name>
                    <val>23</val>
                </param>
                <param>
                    <name>a</name>
                    <val>5</val>
                </param>
                <param>
                    <name>b</name>
                    <val>5</val>
                </param>
            </preset>
        </design>
    </saved-design>
    <saved-design>
        <id>90a45678-0474-455d-af95-13de6c181324</id>
        <ts>2019-04-09T14:38:30.033+01:00</ts>
        <title>j=3,k=3</title>
        <designer>Kit</designer>
        <comment/>
        <design>
            <preset>
                <title>Wikipedia -name unknown</title>
                <scale>100</scale>
                <param>
                    <name>a</name>
                    <val>1</val>
                </param>
                <param>
                    <name>b</name>
                    <val>80</val>
                </param>
                <param>
                    <name>j</name>
                    <val>3</val>
                </param>
                <param>
                    <name>c</name>
                    <val>1</val>
                </param>
                <param>
                    <name>d</name>
                    <val>80</val>
                </param>
                <param>
                    <name>k</name>
                    <val>3</val>
                </param>
            </preset>
        </design>
    </saved-design>
    <saved-design>
        <id>88337fd9-0b29-4bbd-b54c-0828f8e8462d</id>
        <ts>2019-04-10T09:05:53.251+01:00</ts>
        <title>9 loop - 27 crossing briad</title>
        <designer>Kit</designer>
        <comment/>
        <design>
            <preset>
                <title>Fourier 3 Term Relative</title>
                <scale>1</scale>
                <param>
                    <name>R1</name>
                    <val>1</val>
                </param>
                <param>
                    <name>A1</name>
                    <val>80</val>
                </param>
                <param>
                    <name>P1</name>
                    <val>0</val>
                </param>
                <param>
                    <name>R2</name>
                    <val>-9</val>
                </param>
                <param>
                    <name>A2</name>
                    <val>50</val>
                </param>
                <param>
                    <name>P2</name>
                    <val>0</val>
                </param>
                <param>
                    <name>R3</name>
                    <val>30</val>
                </param>
                <param>
                    <name>A3</name>
                    <val>0</val>
                </param>
                <param>
                    <name>P3</name>
                    <val>0</val>
                </param>
            </preset>
        </design>
    </saved-design>
    <saved-design>
        <id>fd86c99b-e5d8-4d73-89ee-56114bb12440</id>
        <ts>2019-04-10T12:22:48.203+01:00</ts>
        <title>Bowen knot</title>
        <designer>Kit</designer>
        <comment/>
        <design>
            <preset>
                <title>Fourier 3 Term Relative</title>
                <scale>1</scale>
                <param>
                    <name>R1</name>
                    <val>1</val>
                </param>
                <param>
                    <name>A1</name>
                    <val>63</val>
                </param>
                <param>
                    <name>P1</name>
                    <val>0</val>
                </param>
                <param>
                    <name>R2</name>
                    <val>-4</val>
                </param>
                <param>
                    <name>A2</name>
                    <val>39</val>
                </param>
                <param>
                    <name>P2</name>
                    <val>0</val>
                </param>
                <param>
                    <name>R3</name>
                    <val>3</val>
                </param>
                <param>
                    <name>A3</name>
                    <val>22</val>
                </param>
                <param>
                    <name>P3</name>
                    <val>90</val>
                </param>
            </preset>
        </design>
    </saved-design>
    <saved-design>
        <id>3cf8c3c1-4cf2-4af5-943b-9f736adaa7fc</id>
        <ts>2019-04-10T17:34:04.268+01:00</ts>
        <title>Pincushion - a Potluck</title>
        <designer>Kit</designer>
        <comment/>
        <design>
            <preset>
                <title>Fourier 3 Term</title>
                <scale>3</scale>
                <param>
                    <name>R1</name>
                    <val>7</val>
                </param>
                <param>
                    <name>A1</name>
                    <val>-45</val>
                </param>
                <param>
                    <name>P1</name>
                    <val>31</val>
                </param>
                <param>
                    <name>R2</name>
                    <val>-7</val>
                </param>
                <param>
                    <name>A2</name>
                    <val>10</val>
                </param>
                <param>
                    <name>P2</name>
                    <val>164</val>
                </param>
                <param>
                    <name>R3</name>
                    <val>76</val>
                </param>
                <param>
                    <name>A3</name>
                    <val>46</val>
                </param>
                <param>
                    <name>P3</name>
                    <val>122</val>
                </param>
            </preset>
        </design>
    </saved-design>
    <saved-design>
        <id>8dd18e0b-8d11-4d3c-91c7-87e629f8938b</id>
        <ts>2019-04-11T15:40:50.825+01:00</ts>
        <title>Emergent square</title>
        <designer>AuntDaisy</designer>
        <comment/>
        <design>
            <preset>
                <title>Fourier 3 Term Relative</title>
                <scale>1</scale>
                <param>
                    <name>R1</name>
                    <val>23</val>
                </param>
                <param>
                    <name>A1</name>
                    <val>-74</val>
                </param>
                <param>
                    <name>P1</name>
                    <val>158</val>
                </param>
                <param>
                    <name>R2</name>
                    <val>-49</val>
                </param>
                <param>
                    <name>A2</name>
                    <val>23</val>
                </param>
                <param>
                    <name>P2</name>
                    <val>156</val>
                </param>
                <param>
                    <name>R3</name>
                    <val>-43</val>
                </param>
                <param>
                    <name>A3</name>
                    <val>-7</val>
                </param>
                <param>
                    <name>P3</name>
                    <val>19</val>
                </param>
            </preset>
        </design>
    </saved-design>
    <saved-design>
        <id>f1e38d5d-c699-4649-a78c-124ca5ac36a7</id>
        <ts>2019-04-11T15:59:46.971+01:00</ts>
        <title>Zero</title>
        <designer>AuntDaisy</designer>
        <comment>CLose to the Zero character</comment>
        <design>
            <preset>
                <title>Fourier 3 Term Relative</title>
                <scale>1</scale>
                <param>
                    <name>R1</name>
                    <val>16</val>
                </param>
                <param>
                    <name>A1</name>
                    <val>100</val>
                </param>
                <param>
                    <name>P1</name>
                    <val>60</val>
                </param>
                <param>
                    <name>R2</name>
                    <val>32</val>
                </param>
                <param>
                    <name>A2</name>
                    <val>13</val>
                </param>
                <param>
                    <name>P2</name>
                    <val>0</val>
                </param>
                <param>
                    <name>R3</name>
                    <val>13</val>
                </param>
                <param>
                    <name>A3</name>
                    <val>24</val>
                </param>
                <param>
                    <name>P3</name>
                    <val>0</val>
                </param>
            </preset>
        </design>
    </saved-design>
    <saved-design>
        <id>4c3b7b70-1606-431f-9de8-d5a6c37ad664</id>
        <ts>2019-04-12T20:14:05.7+01:00</ts>
        <title>donut</title>
        <designer>Kit</designer>
        <comment/>
        <design>
            <preset>
                <title>Wikipedia -name unknown-reduced</title>
                <scale>100</scale>
                <param>
                    <name>a</name>
                    <val>1</val>
                </param>
                <param>
                    <name>b</name>
                    <val>50</val>
                </param>
                <param>
                    <name>j</name>
                    <val>3</val>
                </param>
                <param>
                    <name>k</name>
                    <val>3</val>
                </param>
                <param>
                    <name>p</name>
                    <val>127</val>
                </param>
            </preset>
        </design>
    </saved-design>
    <saved-design>
        <id>a0aa1f42-70db-4398-ab71-07bc73f25cec</id>
        <ts>2019-04-13T21:26:23.422+01:00</ts>
        <title>heartline</title>
        <designer>Kit</designer>
        <comment/>
        <design>
            <preset>
                <title>Fourier 3 Term Relative</title>
                <scale>1</scale>
                <param>
                    <name>R1</name>
                    <val>7</val>
                </param>
                <param>
                    <name>A1</name>
                    <val>-94</val>
                </param>
                <param>
                    <name>P1</name>
                    <val>144</val>
                </param>
                <param>
                    <name>R2</name>
                    <val>29</val>
                </param>
                <param>
                    <name>A2</name>
                    <val>-96</val>
                </param>
                <param>
                    <name>P2</name>
                    <val>31</val>
                </param>
                <param>
                    <name>R3</name>
                    <val>7</val>
                </param>
                <param>
                    <name>A3</name>
                    <val>62</val>
                </param>
                <param>
                    <name>P3</name>
                    <val>84</val>
                </param>
            </preset>
        </design>
    </saved-design>
    <saved-design>
        <id>af7edd26-0c5d-467a-a71c-f5415567b2c1</id>
        <ts>2019-06-08T22:45:12.557+01:00</ts>
        <title>Snake</title>
        <designer>Kit</designer>
        <comment/>
        <design>
            <preset>
                <title>Double Linkage</title>
                <scale>10</scale>
                <stepsize>1</stepsize>
                <maxcycles>30</maxcycles>
                <param>
                    <name>AR</name>
                    <val>5</val>
                </param>
                <param>
                    <name>Ar</name>
                    <val>8</val>
                </param>
                <param>
                    <name>Al</name>
                    <val>15</val>
                </param>
                <param>
                    <name>Ap</name>
                    <val>40</val>
                </param>
                <param>
                    <name>BR</name>
                    <val>5</val>
                </param>
                <param>
                    <name>Br</name>
                    <val>-4</val>
                </param>
                <param>
                    <name>Bl</name>
                    <val>15</val>
                </param>
                <param>
                    <name>Bp</name>
                    <val>0</val>
                </param>
                <param>
                    <name>AB</name>
                    <val>6</val>
                </param>
                <param>
                    <name>CR</name>
                    <val>1</val>
                </param>
                <param>
                    <name>Cr</name>
                    <val>8.2</val>
                </param>
            </preset>
        </design>
    </saved-design>
    <saved-design>
        <id>d36604e4-b03d-481f-8dff-1394cde82a0c</id>
        <ts>2019-06-09T14:31:23.419+01:00</ts>
        <title>Flow1</title>
        <designer>Kit</designer>
        <comment/>
        <design>
            <preset>
                <title>Double Linkage</title>
                <scale>20</scale>
                <stepsize>1</stepsize>
                <maxcycles>40</maxcycles>
                <param>
                    <name>AR</name>
                    <val>5</val>
                </param>
                <param>
                    <name>Ar</name>
                    <val>1</val>
                </param>
                <param>
                    <name>Al</name>
                    <val>15</val>
                </param>
                <param>
                    <name>Ap</name>
                    <val>164</val>
                </param>
                <param>
                    <name>BR</name>
                    <val>5</val>
                </param>
                <param>
                    <name>Br</name>
                    <val>2.025</val>
                </param>
                <param>
                    <name>Bl</name>
                    <val>13</val>
                </param>
                <param>
                    <name>Bp</name>
                    <val>105</val>
                </param>
                <param>
                    <name>AB</name>
                    <val>5</val>
                </param>
                <param>
                    <name>CR</name>
                    <val>5</val>
                </param>
                <param>
                    <name>Cr</name>
                    <val>2</val>
                </param>
            </preset>
        </design>
    </saved-design>
    <saved-design>
        <id>a87bee5a-7095-4f3a-b2c5-8dcc33fd449a</id>
        <ts>2019-06-09T16:11:07.665+01:00</ts>
        <title>Smoke</title>
        <designer>Kit</designer>
        <comment/>
        <design>
            <preset>
                <title>Double Linkage</title>
                <scale>15</scale>
                <stepsize>.1</stepsize>
                <maxcycles>2</maxcycles>
                <param>
                    <name>AR</name>
                    <val>1</val>
                </param>
                <param>
                    <name>Ar</name>
                    <val>8.1</val>
                </param>
                <param>
                    <name>Al</name>
                    <val>15</val>
                </param>
                <param>
                    <name>Ap</name>
                    <val>34</val>
                </param>
                <param>
                    <name>BR</name>
                    <val>12</val>
                </param>
                <param>
                    <name>Br</name>
                    <val>-4</val>
                </param>
                <param>
                    <name>Bl</name>
                    <val>20</val>
                </param>
                <param>
                    <name>Bp</name>
                    <val>83</val>
                </param>
                <param>
                    <name>AB</name>
                    <val>6</val>
                </param>
                <param>
                    <name>CR</name>
                    <val>1</val>
                </param>
                <param>
                    <name>Cr</name>
                    <val>100</val>
                </param>
            </preset>
        </design>
    </saved-design><!--    
    <saved-design>
        <id>5e7a8d44-9315-49b9-b37c-80622701da22</id>
        <ts>2019-06-09T16:16:04.859+01:00</ts>
        <title>test</title>
        <designer>Kit</designer>
        <comment/>
        <design>
            <preset>
                <title>Double Linkage</title>
                <scale>10</scale>
                <stepsize>1</stepsize>
                <maxcycles>30</maxcycles>
                <param>
                    <name>AR</name>
                    <val>5</val>
                </param>
                <param>
                    <name>Ar</name>
                    <val>8</val>
                </param>
                <param>
                    <name>Al</name>
                    <val>15</val>
                </param>
                <param>
                    <name>Ap</name>
                    <val>40</val>
                </param>
                <param>
                    <name>BR</name>
                    <val>5</val>
                </param>
                <param>
                    <name>Br</name>
                    <val>-4</val>
                </param>
                <param>
                    <name>Bl</name>
                    <val>15</val>
                </param>
                <param>
                    <name>Bp</name>
                    <val>0</val>
                </param>
                <param>
                    <name>AB</name>
                    <val>7</val>
                </param>
                <param>
                    <name>CR</name>
                    <val>1</val>
                </param>
                <param>
                    <name>Cr</name>
                    <val>8.2</val>
                </param>
            </preset>
        </design>
    </saved-design>
    -->
    <saved-design>
        <id>447213d4-e581-4c35-93f2-a3c81c558ac9</id>
        <ts>2019-06-10T22:01:12.05+01:00</ts>
        <title>A2</title>
        <designer>Lorenzo/Kit</designer>
        <comment/>
        <design>
            <preset>
                <title>Double Linkage</title>
                <scale>1</scale>
                <stepsize>1</stepsize>
                <maxcycles>20</maxcycles>
                <param>
                    <name>AR</name>
                    <val>4</val>
                </param>
                <param>
                    <name>Ar</name>
                    <val>7</val>
                </param>
                <param>
                    <name>Al</name>
                    <val>90</val>
                </param>
                <param>
                    <name>Ap</name>
                    <val>0</val>
                </param>
                <param>
                    <name>BR</name>
                    <val>24</val>
                </param>
                <param>
                    <name>Br</name>
                    <val>-5.88</val>
                </param>
                <param>
                    <name>Bl</name>
                    <val>120</val>
                </param>
                <param>
                    <name>Bp</name>
                    <val>0</val>
                </param>
                <param>
                    <name>AB</name>
                    <val>140</val>
                </param>
                <param>
                    <name>CR</name>
                    <val>100</val>
                </param>
                <param>
                    <name>Cr</name>
                    <val>1</val>
                </param>
                <param>
                    <name>Cp</name>
                    <val>32</val>
                </param>
            </preset>
        </design>
    </saved-design>
    <saved-design>
        <id>abf44033-42ba-4d90-8470-e6845e6c0032</id>
        <ts>2019-06-10T22:07:59.461+01:00</ts>
        <title>A3</title>
        <designer>Lorenzo/Kit</designer>
        <comment/>
        <design>
            <preset>
                <title>Double Linkage</title>
                <scale>2</scale>
                <stepsize>1</stepsize>
                <maxcycles>30</maxcycles>
                <param>
                    <name>AR</name>
                    <val>4</val>
                </param>
                <param>
                    <name>Ar</name>
                    <val>6</val>
                </param>
                <param>
                    <name>Al</name>
                    <val>90</val>
                </param>
                <param>
                    <name>Ap</name>
                    <val>0</val>
                </param>
                <param>
                    <name>BR</name>
                    <val>20</val>
                </param>
                <param>
                    <name>Br</name>
                    <val>5.02</val>
                </param>
                <param>
                    <name>Bl</name>
                    <val>120</val>
                </param>
                <param>
                    <name>Bp</name>
                    <val>0</val>
                </param>
                <param>
                    <name>AB</name>
                    <val>100</val>
                </param>
                <param>
                    <name>CR</name>
                    <val>100</val>
                </param>
                <param>
                    <name>Cr</name>
                    <val>1</val>
                </param>
                <param>
                    <name>Cp</name>
                    <val>27</val>
                </param>
            </preset>
        </design>
    </saved-design>
    <saved-design>
        <id>8f873444-a681-419b-aa5d-b8ca4fd4510d</id>
        <ts>2019-06-11T22:47:46.652+01:00</ts>
        <title>alt1</title>
        <designer>kit</designer>
        <comment/>
        <design>
            <preset>
                <title>Double Linkage V2</title>
                <scale>3</scale>
                <stepsize>1</stepsize>
                <maxcycles>10</maxcycles>
                <param>
                    <name>AR</name>
                    <val>14</val>
                </param>
                <param>
                    <name>Ar</name>
                    <val>8.01</val>
                </param>
                <param>
                    <name>AD</name>
                    <val>84</val>
                </param>
                <param>
                    <name>Ap</name>
                    <val>68</val>
                </param>
                <param>
                    <name>BR</name>
                    <val>7</val>
                </param>
                <param>
                    <name>Br</name>
                    <val>9</val>
                </param>
                <param>
                    <name>BD</name>
                    <val>88</val>
                </param>
                <param>
                    <name>Bp</name>
                    <val>135</val>
                </param>
                <param>
                    <name>AB</name>
                    <val>33</val>
                </param>
                <param>
                    <name>CR</name>
                    <val>30</val>
                </param>
                <param>
                    <name>Cr</name>
                    <val>-5</val>
                </param>
                <param>
                    <name>Cp</name>
                    <val>0</val>
                </param>
            </preset>
        </design>
    </saved-design>
    <saved-design>
        <id>78ea9a0d-ece4-49e8-912c-aaece859d1f6</id>
        <ts>2019-06-18T23:44:41.738+01:00</ts>
        <title>double</title>
        <designer>Kit</designer>
        <comment/>
        <design>
            <preset>
                <title>Double Linkage V2</title>
                <scale>20</scale>
                <stepsize>1</stepsize>
                <maxcycles>50</maxcycles>
                <param>
                    <name>AR</name>
                    <val>5</val>
                </param>
                <param>
                    <name>Ar</name>
                    <val>2.02</val>
                </param>
                <param>
                    <name>AD</name>
                    <val>53</val>
                </param>
                <param>
                    <name>Ap</name>
                    <val>0</val>
                </param>
                <param>
                    <name>BR</name>
                    <val>0</val>
                </param>
                <param>
                    <name>Br</name>
                    <val>-2</val>
                </param>
                <param>
                    <name>BD</name>
                    <val>55</val>
                </param>
                <param>
                    <name>Bp</name>
                    <val>180</val>
                </param>
                <param>
                    <name>AB</name>
                    <val>55</val>
                </param>
                <param>
                    <name>CR</name>
                    <val>6</val>
                </param>
                <param>
                    <name>Cr</name>
                    <val>-1</val>
                </param>
                <param>
                    <name>Cp</name>
                    <val>1</val>
                </param>
            </preset>
        </design>
    </saved-design>
    <saved-design>
        <id>9b459029-3517-4d03-830f-6dc1b1c48b79</id>
        <ts>2019-12-08T16:14:45.367Z</ts>
        <title>another go at Lorenzos</title>
        <designer>Kit</designer>
        <comment/>
        <design>
            <preset>
                <title>Double Linkage V3</title>
                <scale>3</scale>
                <stepsize>1</stepsize>
                <maxcycles>100</maxcycles>
                <param>
                    <name>AR</name>
                    <val>5</val>
                </param>
                <param>
                    <name>Ar</name>
                    <val>7</val>
                </param>
                <param>
                    <name>AD</name>
                    <val>16</val>
                </param>
                <param>
                    <name>Ap</name>
                    <val>218</val>
                </param>
                <param>
                    <name>BR</name>
                    <val>5</val>
                </param>
                <param>
                    <name>Br</name>
                    <val>-5.88</val>
                </param>
                <param>
                    <name>BD</name>
                    <val>16</val>
                </param>
                <param>
                    <name>Bp</name>
                    <val>180</val>
                </param>
                <param>
                    <name>AB</name>
                    <val>12</val>
                </param>
                <param>
                    <name>CR</name>
                    <val>51</val>
                </param>
                <param>
                    <name>Cr</name>
                    <val>1</val>
                </param>
                <param>
                    <name>Cp</name>
                    <val>0</val>
                </param>
                <param>
                    <name>check</name>
                    <val>1</val>
                </param>
                <param>
                    <name>log</name>
                    <val>0</val>
                </param>
            </preset>
        </design>
    </saved-design>
    <saved-design>
        <id>1eb9bb7c-0005-4a3a-8f1b-235da57f73a6</id>
        <ts>2019-12-08T18:42:18.56Z</ts>
        <title>Multiple trefoils</title>
        <designer>Kit</designer>
        <comment/>
        <design>
            <preset>
                <title>Fourier 3 Term Relative</title>
                <scale>1</scale>
                <stepsize>0.1</stepsize>
                <maxcycles>100</maxcycles>
                <param>
                    <name>R1</name>
                    <val>1</val>
                </param>
                <param>
                    <name>A1</name>
                    <val>100</val>
                </param>
                <param>
                    <name>P1</name>
                    <val>0</val>
                </param>
                <param>
                    <name>R2</name>
                    <val>6</val>
                </param>
                <param>
                    <name>A2</name>
                    <val>39</val>
                </param>
                <param>
                    <name>P2</name>
                    <val>0</val>
                </param>
                <param>
                    <name>R3</name>
                    <val>-12</val>
                </param>
                <param>
                    <name>A3</name>
                    <val>-32</val>
                </param>
                <param>
                    <name>P3</name>
                    <val>1</val>
                </param>
            </preset>
        </design>
    </saved-design>
    <saved-design>
        <id>8e8ec1df-7a7e-4243-a90b-a0bdd05d9301</id>
        <ts>2020-04-29T22:31:38.94+01:00</ts>
        <title>pendulum 1</title>
        <designer>kit</designer>
        <comment/>
        <design>
            <preset>
                <title>Harmonograph</title>
                <scale>20</scale>
                <stepsize>1</stepsize>
                <maxcycles>50</maxcycles>
                <param>
                    <name>Ax</name>
                    <val>4.95</val>
                </param>
                <param>
                    <name>Ay</name>
                    <val>0</val>
                </param>
                <param>
                    <name>APx</name>
                    <val>50</val>
                </param>
                <param>
                    <name>APy</name>
                    <val>0</val>
                </param>
                <param>
                    <name>AF</name>
                    <val>1</val>
                </param>
                <param>
                    <name>AD</name>
                    <val>50</val>
                </param>
                <param>
                    <name>Bx</name>
                    <val>0</val>
                </param>
                <param>
                    <name>By</name>
                    <val>5</val>
                </param>
                <param>
                    <name>BPx</name>
                    <val>0</val>
                </param>
                <param>
                    <name>BPy</name>
                    <val>90</val>
                </param>
                <param>
                    <name>BF</name>
                    <val>1.5</val>
                </param>
                <param>
                    <name>BD</name>
                    <val>50</val>
                </param>
                <param>
                    <name>Cx</name>
                    <val>0</val>
                </param>
                <param>
                    <name>Cy</name>
                    <val>5</val>
                </param>
                <param>
                    <name>CPx</name>
                    <val>0</val>
                </param>
                <param>
                    <name>CPy</name>
                    <val>0</val>
                </param>
                <param>
                    <name>CF</name>
                    <val>1</val>
                </param>
                <param>
                    <name>CD</name>
                    <val>50</val>
                </param>
                <param>
                    <name>log</name>
                    <val>0</val>
                </param>
            </preset>
        </design>
    </saved-design>
</saved>
